ssml_maker/__init__.py
ssml_maker/ssml_maker.py
ssml_maker-0.1.1.dist-info/LICENSE
ssml_maker-0.1.1.dist-info/METADATA
ssml_maker-0.1.1.dist-info/WHEEL
ssml_maker-0.1.1.dist-info/top_level.txt
ssml_maker-0.1.1.dist-info/RECORD
